django_anonymous/__init__.py
django_anonymous/anonymizer.py
django_anonymous/faker.py
django_anonymous/register.py
django_anonymous/management/__init__.py
django_anonymous/management/commands/__init__.py
django_anonymous/management/commands/anonymize.py
django_anonymous-0.4.0.dist-info/LICENSE
django_anonymous-0.4.0.dist-info/METADATA
django_anonymous-0.4.0.dist-info/WHEEL
django_anonymous-0.4.0.dist-info/top_level.txt
django_anonymous-0.4.0.dist-info/RECORD
