Metadata-Version: 2.1
Name: django-anonymous
Version: 0.4.0
Summary: Simple Djanngo module to anonymize production data for safe usage on none production environments
Home-page: https://github.com/fourdigits/django-anonymous
Author: Maikel Martens
Author-email: maikel@fourdigits.nl
License: GPL3
Download-URL: https://github.com/fourdigits/django-anonymous/releases/tag/0.4.0
Keywords: Django,anonymous,anonymize
Platform: any
Classifier: Development Status :: 5 - Production/Stable
Classifier: Intended Audience :: Developers
Classifier: License :: OSI Approved :: GNU General Public License v3 (GPLv3)
Classifier: Operating System :: OS Independent
Classifier: Framework :: Django
Classifier: Programming Language :: Python
Classifier: Programming Language :: Python :: 3
Requires-Python: >=3.6
License-File: LICENSE
Requires-Dist: Faker
Requires-Dist: tqdm
